hoehoe/__init__.py
hoehoe/advert.py
hoehoe/exceptions.py
hoehoe/page.py
hoehoe/utils.py
hoehoe-1.0.0.dist-info/LICENSE
hoehoe-1.0.0.dist-info/METADATA
hoehoe-1.0.0.dist-info/WHEEL
hoehoe-1.0.0.dist-info/top_level.txt
hoehoe-1.0.0.dist-info/RECORD
