Metadata-Version: 2.1
Name: hoehoe
Version: 1.0.0
Summary: Rox crawler
Home-page: https://github.com/dwabece/rox
Author: MJ Krakowski
Author-email: packaging@c40.pl
License: UNKNOWN
Platform: UNKNOWN
Classifier: Programming Language :: Python :: 3
Classifier: License :: OSI Approved :: MIT License
Classifier: Operating System :: OS Independent
Requires-Python: >=3.6
Requires-Dist: beautifulsoup4
Requires-Dist: requests
Requires-Dist: requests-html
Requires-Dist: click
